pybromo/__init__.py
pybromo/_version.py
pybromo/brownian.py
pybromo/brownian_plot.py
pybromo/brownian_tests_extra.py
pybromo/diffusion.py
pybromo/iter_chunks.py
pybromo/legacy.py
pybromo/loadutils.py
pybromo/path_def.py
pybromo/plot.py
pybromo/psflib.py
pybromo/scroll_gui.py
pybromo/storage.py
pybromo/test_PSFLab_matrix.py
pybromo/timestamps.py
pybromo/__pycache__/__init__.cpython-34.pyc
pybromo/__pycache__/_version.cpython-34.pyc
pybromo/__pycache__/test_PSFLab_matrix.cpython-34-PYTEST.pyc
pybromo/psf_data/xz_realistic_z50_150_160_580nm_n1335_HR2.mat
pybromo/tests/__init__.py
pybromo/tests/test_diffusion.py
pybromo/utils/__init__.py
pybromo/utils/git.py
pybromo/utils/hdf5.py
pybromo-0.5.dist-info/DESCRIPTION.rst
pybromo-0.5.dist-info/METADATA
pybromo-0.5.dist-info/metadata.json
pybromo-0.5.dist-info/pbr.json
pybromo-0.5.dist-info/RECORD
pybromo-0.5.dist-info/top_level.txt
pybromo-0.5.dist-info/WHEEL
