Metadata-Version: 2.0
Name: pybromo
Version: 0.5
Summary: Simulator for confocal single-molecule fluorescence experiments.
Home-page: https://github.com/tritemio/PyBroMo
Author: Antonino Ingargiola
Author-email: tritemio@gmail.com
License: GPLv2
Download-URL: https://github.com/tritemio/PyBroMo
Keywords: single-molecule FRET smFRET biophysics confocal freely-diffusing brownian-motion simulator
Platform: Windows
Platform: Linux
Platform: Mac OS X
Classifier: Intended Audience :: Science/Research
Classifier: Operating System :: OS Independent
Classifier: Programming Language :: Python
Classifier: Programming Language :: Python :: 2.7
Classifier: Programming Language :: Python :: 3.4
Classifier: Topic :: Scientific/Engineering
Requires-Dist: numpy
Requires-Dist: setuptools
Requires-Dist: tables
Requires-Dist: matplotlib
Requires-Dist: future
